wn/__main__.py
watch_norminette-0.0.3.dist-info/LICENSE
watch_norminette-0.0.3.dist-info/METADATA
watch_norminette-0.0.3.dist-info/WHEEL
watch_norminette-0.0.3.dist-info/entry_points.txt
watch_norminette-0.0.3.dist-info/top_level.txt
watch_norminette-0.0.3.dist-info/RECORD
