Metadata-Version: 2.1
Name: watch-norminette
Version: 0.0.3
Summary: Um script em Python que fica observando uma pasta e rodando o norminette nos arquivos quando forem salvos
Home-page: https://github.com/NiumXp/watch-norminette
Author: NiumXp
License: GNU General Public License v3.0
Platform: UNKNOWN
Classifier: Development Status :: 5 - Production/Stable
Classifier: Natural Language :: Portuguese (Brazilian)
Classifier: Operating System :: OS Independent
Classifier: Programming Language :: Python :: 3.7
Classifier: Programming Language :: Python :: 3.8
Classifier: Programming Language :: Python :: 3.9
Classifier: Programming Language :: Python :: 3.10
Classifier: Topic :: Utilities
Requires-Python: >=3.7.0
License-File: LICENSE
